quiz_gen/__init__.py
quiz_gen/__version__.py
quiz_gen/cli.py
quiz_gen/agents/__init__.py
quiz_gen/agents/conceptual_generator.py
quiz_gen/agents/config.py
quiz_gen/agents/judge.py
quiz_gen/agents/practical_generator.py
quiz_gen/agents/validator.py
quiz_gen/agents/workflow.py
quiz_gen/models/__init__.py
quiz_gen/models/chunk.py
quiz_gen/models/document.py
quiz_gen/models/question.py
quiz_gen/models/quiz.py
quiz_gen/parsers/__init__.py
quiz_gen/parsers/base.py
quiz_gen/parsers/pdf_parser.py
quiz_gen/parsers/utils.py
quiz_gen/parsers/html/eur_lex_parser.py
quiz_gen/storage/__init__.py
quiz_gen/storage/base.py
quiz_gen/storage/database.py
quiz_gen/storage/json_storage.py
quiz_gen/utils/__init__.py
quiz_gen/utils/helpers.py
quiz_gen/utils/logging.py
quiz_gen/validation/__init__.py
quiz_gen/validation/human_feedback.py
quiz_gen/validation/quality_checker.py
quiz_gen-0.2.8.dist-info/licenses/LICENSE
quiz_gen-0.2.8.dist-info/METADATA
quiz_gen-0.2.8.dist-info/WHEEL
quiz_gen-0.2.8.dist-info/entry_points.txt
quiz_gen-0.2.8.dist-info/top_level.txt
quiz_gen-0.2.8.dist-info/RECORD
