Metadata-Version: 2.4
Name: quiz-gen
Version: 0.2.8
Summary: AI-powered quiz generator for regulatory, certification, and educational documentation
Author: Yauheniya Varabyova
License-Expression: MIT
Project-URL: Documentation, https://quiz-gen.readthedocs.io
Project-URL: Repository, https://github.com/yauheniya-ai/quiz-gen
Keywords: quiz,regulation,certification,education,eur-lex,cfr
Classifier: Development Status :: 3 - Alpha
Classifier: Intended Audience :: Education
Classifier: Intended Audience :: Developers
Classifier: Programming Language :: Python :: 3
Classifier: Programming Language :: Python :: 3.10
Classifier: Programming Language :: Python :: 3.11
Classifier: Programming Language :: Python :: 3.12
Classifier: Programming Language :: Python :: 3.13
Requires-Python: >=3.10
License-File: LICENSE
Requires-Dist: beautifulsoup4>=4.12.0
Requires-Dist: lxml>=5.0.0
Requires-Dist: requests>=2.31.0
Requires-Dist: langgraph
Requires-Dist: openai
Requires-Dist: anthropic
Requires-Dist: python-dotenv
Provides-Extra: dev
Requires-Dist: pytest>=7.4.0; extra == "dev"
Requires-Dist: pytest-cov>=4.1.0; extra == "dev"
Requires-Dist: black>=23.0.0; extra == "dev"
Requires-Dist: ruff>=0.1.0; extra == "dev"
Requires-Dist: mypy>=1.5.0; extra == "dev"
Requires-Dist: pre-commit>=3.4.0; extra == "dev"
Requires-Dist: twine>=4.0.0; extra == "dev"
Requires-Dist: mkdocs; extra == "dev"
Requires-Dist: mkdocs-material; extra == "dev"
Dynamic: license-file
